endanditon/__init__.py
endanditon-0.1.dist-info/LICENSE.txt
endanditon-0.1.dist-info/METADATA
endanditon-0.1.dist-info/WHEEL
endanditon-0.1.dist-info/top_level.txt
endanditon-0.1.dist-info/RECORD
