Metadata-Version: 2.1
Name: endanditon
Version: 0.1
Summary: Una libreria un po scemonita ma poco carina alla vista
Home-page: UNKNOWN
Author: Rocco Rosso
Author-email: roccorosso@gmail.com
License: UNKNOWN
Platform: UNKNOWN
Classifier: Programming Language :: Python :: 3
Classifier: License :: OSI Approved :: MIT License
Classifier: Operating System :: OS Independent
License-File: LICENSE.txt
